examples/__init__.py
examples/advanced_transformations.py
examples/basic_usage.py
examples/data_migration.py
examples/performance_analysis.py
examples/run_all_examples.py
examples/verify_metadata.py
vertica_sqlglot_dialect/__init__.py
vertica_sqlglot_dialect/vertica.py
vertica_sqlglot_dialect-0.1.7.dist-info/licenses/LICENSE
vertica_sqlglot_dialect-0.1.7.dist-info/METADATA
vertica_sqlglot_dialect-0.1.7.dist-info/WHEEL
vertica_sqlglot_dialect-0.1.7.dist-info/entry_points.txt
vertica_sqlglot_dialect-0.1.7.dist-info/top_level.txt
vertica_sqlglot_dialect-0.1.7.dist-info/RECORD
