Metadata-Version: 2.4
Name: vertica-sqlglot-dialect
Version: 0.1.7
Summary: Vertica SQL dialect implementation for sqlglot
Author-email: Luis de la Torre <luisdelatorre012@gmail.com>
License-Expression: MIT
Project-URL: Homepage, https://github.com/luisdelatorre/vertica-sqlglot-dialect
Project-URL: Repository, https://github.com/luisdelatorre/vertica-sqlglot-dialect
Project-URL: Issues, https://github.com/luisdelatorre/vertica-sqlglot-dialect/issues
Project-URL: Documentation, https://github.com/luisdelatorre/vertica-sqlglot-dialect#readme
Keywords: sql,vertica,sqlglot,dialect,parser,sql-parser
Classifier: Development Status :: 3 - Alpha
Classifier: Intended Audience :: Developers
Classifier: Programming Language :: Python :: 3
Classifier: Programming Language :: Python :: 3.11
Classifier: Programming Language :: Python :: 3.12
Classifier: Programming Language :: Python :: 3.13
Classifier: Topic :: Database
Classifier: Topic :: Software Development :: Libraries :: Python Modules
Requires-Python: >=3.11
License-File: LICENSE
Requires-Dist: sqlglot>=26.0.0
Provides-Extra: dev
Requires-Dist: pytest>=7.0.0; extra == "dev"
Requires-Dist: pytest-cov>=4.0.0; extra == "dev"
Requires-Dist: black>=22.0.0; extra == "dev"
Requires-Dist: isort>=5.0.0; extra == "dev"
Requires-Dist: mypy>=1.0.0; extra == "dev"
Dynamic: license-file
